mri_datasets/__about__.py
mri_datasets/__init__.py
mri_datasets/ocmr/__init__.py
mri_datasets/ocmr/ocmr.py
mri_datasets/ocmr/ocmr_data_attributes.csv
mri_datasets/ocmr/ocmr_reader.py
mri_datasets/ocmr/ocmr_test.py
mri_datasets-0.1.0.dist-info/LICENSE
mri_datasets-0.1.0.dist-info/METADATA
mri_datasets-0.1.0.dist-info/WHEEL
mri_datasets-0.1.0.dist-info/top_level.txt
mri_datasets-0.1.0.dist-info/zip-safe
mri_datasets-0.1.0.dist-info/RECORD
