Metadata-Version: 2.1
Name: mri-datasets
Version: 0.1.0
Summary: A collection of MRI datasets.
Home-page: https://github.com/mrphys/mri-datasets
Author: Javier Montalt Tordera
Author-email: javier.montalt@outlook.com
License: Apache 2.0
Keywords: tensorflow,keras,machine learning,ml
Platform: UNKNOWN
Classifier: Development Status :: 3 - Alpha
Classifier: Environment :: GPU
Classifier: Environment :: GPU :: NVIDIA CUDA
Classifier: Intended Audience :: Developers
Classifier: Intended Audience :: Science/Research
Classifier: License :: OSI Approved :: Apache Software License
Classifier: Operating System :: OS Independent
Classifier: Programming Language :: C++
Classifier: Programming Language :: Python :: 3
Classifier: Programming Language :: Python :: 3.7
Classifier: Programming Language :: Python :: 3.8
Classifier: Programming Language :: Python :: 3.9
Classifier: Topic :: Scientific/Engineering :: Mathematics
Classifier: Topic :: Software Development :: Libraries
Classifier: Topic :: Software Development :: Libraries :: Python Modules
Requires-Python: >=3.7
License-File: LICENSE
Requires-Dist: ismrmrd
Requires-Dist: tensorflow-datasets (>=4.4.0)
